deeplazy/__init__.py
deeplazy/core/__init__.py
deeplazy/core/lazy_cache.py
deeplazy/core/lazy_model.py
deeplazy/core/lazy_redis_cache.py
deeplazy/core/lazy_tensor_loader.py
deeplazy/core/pytorch_lazy_model_patcher.py
deeplazy/core/tensorflow_lazy_model_patcher.py
deeplazy/enums/__init__.py
deeplazy/enums/framework_enum.py
deeplazy/ui/__init__.py
deeplazy/ui/dashboard_monitor.py
deeplazy-1.0.5.dist-info/LICENSE
deeplazy-1.0.5.dist-info/METADATA
deeplazy-1.0.5.dist-info/WHEEL
deeplazy-1.0.5.dist-info/top_level.txt
deeplazy-1.0.5.dist-info/RECORD
