Metadata-Version: 2.2
Name: deeplazy
Version: 1.0.5
Summary: Lazy loading framework for large-scale LLMs using safetensors.
Home-page: https://github.com/yourorg/deeplazy
Author: Eduardo de Moraes Froes
Author-email: eduardomfroes@gmail.com
License: MIT
Classifier: Programming Language :: Python :: 3
Classifier: License :: OSI Approved :: MIT License
Classifier: Operating System :: OS Independent
Requires-Python: >=3.7
License-File: LICENSE
Requires-Dist: torch
Requires-Dist: tensorflow
Requires-Dist: safetensors
Requires-Dist: psutil
Requires-Dist: rich
Requires-Dist: redis
Dynamic: author
Dynamic: author-email
Dynamic: classifier
Dynamic: description
Dynamic: description-content-type
Dynamic: home-page
Dynamic: requires-dist
Dynamic: requires-python
Dynamic: summary
